jellyshuf/__init__.py
jellyshuf/data.py
jellyshuf/jellyfin.py
jellyshuf/shared.py
jellyshuf-0.3.0.dist-info/LICENSE
jellyshuf-0.3.0.dist-info/METADATA
jellyshuf-0.3.0.dist-info/WHEEL
jellyshuf-0.3.0.dist-info/entry_points.txt
jellyshuf-0.3.0.dist-info/top_level.txt
jellyshuf-0.3.0.dist-info/RECORD
