Metadata-Version: 2.1
Name: jellyshuf
Version: 0.3.0
Summary: Randomly add items to mpd queue from jellyfin (use in tandem with mopidy-jellyfin)
Home-page: https://github.com/deafmute1/jellyshuf
Author: Ethan Djeric
Author-email: ethan@ethandjeric.com
License: UNKNOWN
Project-URL: Bug Tracker, https://github.com/deafmute1/jellyshuf/issues
Platform: UNKNOWN
Classifier: Programming Language :: Python :: 3
Classifier: License :: OSI Approved :: MIT License
Classifier: Operating System :: OS Independent
Requires-Python: >=3.8
License-File: LICENSE
Requires-Dist: requests
Requires-Dist: python-musicpd
Requires-Dist: appdirs
Requires-Dist: keyring
